sharpython/__init__.py
sharpython-0.0.0.dist-info/METADATA
sharpython-0.0.0.dist-info/WHEEL
sharpython-0.0.0.dist-info/top_level.txt
sharpython-0.0.0.dist-info/RECORD
