Metadata-Version: 2.1
Name: sharpython
Version: 0.0.0
Summary: Python code compiler.
Home-page: https://github.com/0dminnimda/sharpython-release
Author: 0dminnimda
Author-email: 0dminnimda.contact@gmail.com
License: UNKNOWN
Project-URL: Bug tracker, https://github.com/0dminnimda/sharpython-release/issues
Platform: UNKNOWN
Classifier: Development Status :: 1 - Planning
Classifier: Intended Audience :: Developers
Classifier: Programming Language :: Python
Classifier: Programming Language :: Python :: 3
Classifier: Programming Language :: Python :: 3 :: Only
Classifier: Programming Language :: Python :: 3.6
Classifier: Programming Language :: Python :: 3.7
Classifier: Programming Language :: Python :: 3.8
Classifier: Programming Language :: Python :: 3.9
Classifier: Topic :: Software Development :: Libraries :: Python Modules
Classifier: Topic :: Software Development :: Pre-processors
Classifier: Topic :: Utilities
Classifier: Typing :: Typed
Requires-Python: >=3.6
